cellfinder_visualize/__init__.py
cellfinder_visualize/main.py
cellfinder_visualize/process_summary.py
cellfinder_visualize/region_groupings.py
cellfinder_visualize/render.py
cellfinder_visualize/rendering_functions.py
cellfinder_visualize-0.2.3.dist-info/LICENSE
cellfinder_visualize-0.2.3.dist-info/METADATA
cellfinder_visualize-0.2.3.dist-info/WHEEL
cellfinder_visualize-0.2.3.dist-info/entry_points.txt
cellfinder_visualize-0.2.3.dist-info/top_level.txt
cellfinder_visualize-0.2.3.dist-info/RECORD
