Metadata-Version: 2.1
Name: cellfinder-visualize
Version: 0.2.3
Summary: Cellfinder output visualization
Author-email: Stephen Lenzi <s.lenzi@ucl.ac.uk>
License: BSD-3-Clause
Project-URL: homepage, https://github.com/brainglobe/cellfinder-visualize
Project-URL: bug_tracker, https://github.com/brainglobe/cellfinder-visualize/issues
Project-URL: documentation, https://github.com/brainglobe/cellfinder-visualize
Project-URL: source_code, https://github.com/brainglobe/cellfinder-visualize
Project-URL: user_support, https://github.com/brainglobe/cellfinder-visualize/issues
Classifier: Development Status :: 2 - Pre-Alpha
Classifier: Programming Language :: Python
Classifier: Programming Language :: Python :: 3
Classifier: Programming Language :: Python :: 3.8
Classifier: Programming Language :: Python :: 3.9
Classifier: Programming Language :: Python :: 3.10
Classifier: Operating System :: OS Independent
Classifier: License :: OSI Approved :: BSD License
Requires-Python: >=3.8.0
License-File: LICENSE
Requires-Dist: brainrender
Requires-Dist: fire
Requires-Dist: numpy
Requires-Dist: pandas
Requires-Dist: matplotlib
Requires-Dist: scikit-image
Requires-Dist: Pillow
Requires-Dist: scipy
Requires-Dist: pyside2
Requires-Dist: fancylog
Requires-Dist: seaborn
Requires-Dist: vedo (==2021.0.5)
Requires-Dist: magicgui
Requires-Dist: makefig
Provides-Extra: dev
Requires-Dist: pytest ; extra == 'dev'
Requires-Dist: pytest-cov ; extra == 'dev'
Requires-Dist: coverage ; extra == 'dev'
Requires-Dist: tox ; extra == 'dev'
Requires-Dist: black ; extra == 'dev'
Requires-Dist: mypy ; extra == 'dev'
Requires-Dist: pre-commit ; extra == 'dev'
Requires-Dist: ruff ; extra == 'dev'
Requires-Dist: setuptools-scm ; extra == 'dev'
